pyblinky/__init__.py
pyblinky/py.typed
pyblinky-4.1.0.dist-info/METADATA
pyblinky-4.1.0.dist-info/WHEEL
pyblinky-4.1.0.dist-info/licenses/LICENSE
pyblinky-4.1.0.dist-info/RECORD
