Metadata-Version: 2.4
Name: pyblinky
Version: 4.1.0
Summary: Belkin brand Wemo plug control
Project-URL: Repository, https://github.com/pdumoulin/blinky.git
Project-URL: Homepage, https://github.com/pdumoulin/blinky
Project-URL: Issues, https://github.com/pdumoulin/blinky/issues
Author-email: Paul Dumoulin <paul.l.dumoulin@gmail.com>
License: The MIT License (MIT)
License-File: LICENSE
Keywords: belkin,smart home,wemo
Requires-Python: >=3.8
Requires-Dist: httpx<2,>=0.23.0
